semantic_kernel_zeusdb/__init__.py
semantic_kernel_zeusdb-0.0.0.dist-info/METADATA
semantic_kernel_zeusdb-0.0.0.dist-info/WHEEL
semantic_kernel_zeusdb-0.0.0.dist-info/top_level.txt
semantic_kernel_zeusdb-0.0.0.dist-info/RECORD
