Metadata-Version: 2.4
Name: semantic-kernel-zeusdb
Version: 0.0.0
Summary: Enterprise AI memory for Microsoft ecosystem: Semantic Kernel planning + ZeusDB vector storage with Azure-native performance.
